{
  "reactNativeComponent": {
    "prefix": "jsrnc",
    "body": [
      "import React, { Component } from 'react';",
      "import { View, Text } from 'react-native';",
      "",
      "export default class ${1:${TM_FILENAME_BASE}} extends Component {",
      "  constructor(props) {",
      "    super(props);",
      "    this.state = {",
      "    };",
      "  }",
      "",
      "  render() {",
      "    return (",
      "      <View>",
      "        <Text> ${2:${TM_FILENAME_BASE}} </Text>",
      "      </View>",
      "    );",
      "  }",
      "}",
      ""
    ],
    "description": "React Native Component"
  },
  "reactNativeComponentExport": {
    "prefix": "jsrnce",
    "body": [
      "import React, { Component } from 'react';",
      "import { View, Text } from 'react-native';",
      "",
      "class ${1:${TM_FILENAME_BASE}} extends Component {",
      "  constructor(props) {",
      "    super(props);",
      "    this.state = {",
      "    };",
      "  }",
      "",
      "  render() {",
      "    return (",
      "      <View>",
      "        <Text> ${2:${TM_FILENAME_BASE}} </Text>",
      "      </View>",
      "    );",
      "  }",
      "}",
      "",
      "export default ${1:${TM_FILENAME_BASE}};",
      ""
    ],
    "description": "React Native Component Export"
  },
  "reactNativePureComponent": {
    "prefix": "jsrnpc",
    "body": [
      "import React, { PureComponent } from 'react';",
      "import {  View, Text } from 'react-native';",
      "",
      "export default class ${0:${TM_FILENAME_BASE}} extends PureComponent {",
      "  constructor(props) {",
      "    super(props);",
      "    this.state = {",
      "    };",
      "  }",
      "",
      "  render() {",
      "    return (",
      "      <View>",
      "        <Text> ${0:componentText} </Text>",
      "      </View>",
      "    );",
      "  }",
      "}",
      ""
    ],
    "description": "React Native PureComponent"
  },
  "reactNativePureComponentExport": {
    "prefix": "jsrnpce",
    "body": [
      "import React, { PureComponent } from 'react';",
      "import {  View, Text } from 'react-native';",
      "",
      "class ${1:componentName} extends PureComponent {",
      "  constructor(props) {",
      "    super(props);",
      "    this.state = {",
      "    };",
      "  }",
      "",
      "  render() {",
      "    return (",
      "      <View>",
      "        <Text> ${0:componentText} </Text>",
      "      </View>",
      "    );",
      "  }",
      "}",
      "",
      "export default ${1:componentName};",
      ""
    ],
    "description": "React Native PureComponent with export"
  },
  "reactNativeComponentStateLess": {
    "prefix": "jsrncsl",
    "body": [
      "import React from 'react';",
      "import { Text, View } from 'react-native';",
      "",
      "const ${1:componentName} = ({",
      "    ${2:params},",
      "}) => (",
      "    <View>",
      "        <Text>${1:textName}</Text>",
      "    </View>",
      ");",
      "",
      "export default ${1:componentName};",
      ""
    ],
    "description": "React Native component stateless"
  },
  "reactNativeComponentStateLessWC": {
    "prefix": "jsrncslwc",
    "body": [
      "import React from 'react';",
      "import { View } from 'react-native';",
      "",
      "const ${1:componentName} = ({",
      "    children, style, ...rest",
      "}) => (",
      "    <View style={style}>",
      "        {children}",
      "    </View>",
      ");",
      "",
      "export default ${1:componentName};",
      ""
    ],
    "description": "React Native component stateless with view children"
  },
  "StyleSheet Style": {
    "prefix": "jsrnss",
    "body": [
      "const styles = StyleSheet.create({",
      "\t$1",
      "});"
    ],
    "description": "React Native Stylesheet"
  },
  "style={...}": {
    "prefix": "jssty",
    "body": "style={{${1}}}",
    "description": "styleProps"
  },
  "justifyContent": {
    "prefix": "jsjust",
    "body": "justifyContent: '${1:center}',",
    "description": "justifyContent"
  },
  "alignItems": {
    "prefix": "jsalign",
    "body": "alignItems: '${1:center}',",
    "description": "alignItems"
  },
  "alignSelf": {
    "prefix": "jsalign",
    "body": "alignSelf: '${1:center}',",
    "description": "alignSelf"
  },
  "alignContent": {
    "prefix": "jsalign",
    "body": "alignContent: '${1}',",
    "description": "alignContent"
  },
  "aspectRatio": {
    "prefix": "jsas",
    "body": "aspectRatio: '${1}',",
    "description": "aspectRatio"
  },
  "borderBottomWidth": {
    "prefix": "jsbor",
    "body": "borderBottomWidth: ${1},",
    "description": "borderBottomWidth"
  },
  "borderLeftWidth": {
    "prefix": "jsbor",
    "body": "borderLeftWidth: ${1},",
    "description": "borderLeftWidth"
  },
  "borderRightWidth": {
    "prefix": "jsbor",
    "body": "borderRightWidth: ${1},",
    "description": "borderRightWidth"
  },
  "borderTopWidth": {
    "prefix": "jsbor",
    "body": "borderTopWidth: ${1},",
    "description": "borderTopWidth"
  },
  "borderWidth": {
    "prefix": "jsbor",
    "body": "borderWidth: ${1},",
    "description": "borderWidth"
  },
  "borderColor": {
    "prefix": "jsbor",
    "body": "borderColor: ${1},",
    "description": "borderColor"
  },
  "borderRadius": {
    "prefix": "jsbor",
    "body": "borderRadius: ${1},",
    "description": "borderRadius"
  },
  "borderLeftColor": {
    "prefix": "jsbor",
    "body": "borderLeftColor: ${1},",
    "description": "borderLeftColor"
  },
  "borderRightColor": {
    "prefix": "jsbor",
    "body": "borderRightColor: ${1},",
    "description": "borderRightColor"
  },
  "borderTopColor": {
    "prefix": "jsbor",
    "body": "borderTopColor: ${1},",
    "description": "borderTopColor"
  },
  "borderBottomColor": {
    "prefix": "jsbor",
    "body": "borderBottomColor: ${1},",
    "description": "borderBottomColor"
  },
  "borderBottomLeftRadius": {
    "prefix": "jsbor",
    "body": "borderBottomLeftRadius: ${1},",
    "description": "borderBottomLeftRadius"
  },
  "borderBottomRightRadius": {
    "prefix": "jsbor",
    "body": "borderBottomRightRadius: ${1},",
    "description": "borderBottomRightRadius"
  },
  "borderTopLeftRadius": {
    "prefix": "jsbor",
    "body": "borderTopLeftRadius: ${1},",
    "description": "borderTopLeftRadius"
  },
  "borderTopRightRadius": {
    "prefix": "jsbor",
    "body": "borderTopRightRadius: ${1},",
    "description": "borderTopRightRadius"
  },
  "backgroundColor": {
    "prefix": "jsbac",
    "body": "backgroundColor: ${1},",
    "description": "backgroundColor"
  },
  "display": {
    "prefix": "jsdi",
    "body": "display: '${1:none}',",
    "description": "display"
  },
  "opacity": {
    "prefix": "jsop",
    "body": "opacity: ${1},",
    "description": "opacity"
  },
  "shadowColor": {
    "prefix": "jssha",
    "body": "shadowColor: '${1:none}',",
    "description": "shadowColor"
  },
  "shadowOffset": {
    "prefix": "jssha",
    "body": "shadowOffset: ${1},",
    "description": "shadowOffset"
  },
  "shadowOpacity": {
    "prefix": "jssha",
    "body": "shadowOpacity: ${1},",
    "description": "shadowOpacity"
  },
  "shadowRadius": {
    "prefix": "jssha",
    "body": "shadowRadius: ${1},",
    "description": "shadowRadius"
  },
  "elevation": {
    "prefix": "jse",
    "body": "elevation: ${1},",
    "description": "elevation"
  },
  "flex": {
    "prefix": "jsflex",
    "body": "flex: ${1},",
    "description": "flex"
  },
  "flexBasis": {
    "prefix": "jsflex",
    "body": "flexBasis: '${1}',",
    "description": "flexBasis"
  },
  "flexDirection": {
    "prefix": "jsflex",
    "body": "flexDirection: '${1:column}',",
    "description": "flexDirection"
  },
  "flexGrow": {
    "prefix": "jsflex",
    "body": "flexGrow: '${1}',",
    "description": "flexGrow"
  },
  "flexShrink": {
    "prefix": "jsflex",
    "body": "flexShrink: '${1}',",
    "description": "flexShrink"
  },
  "flexWrap": {
    "prefix": "jsflex",
    "body": "flexWrap: '${1}',",
    "description": "flexWrap"
  },
  "fontSize": {
    "prefix": "jsfo",
    "body": "fontSize: ${1},",
    "description": "fontSize"
  },
  "fontStyle": {
    "prefix": "jsfo",
    "body": "fontStyle: '${1:normal}',",
    "description": "fontStyle"
  },
  "fontFamily": {
    "prefix": "jsfo",
    "body": "fontFamily: '${1}',",
    "description": "fontFamily"
  },
  "fontWeight": {
    "prefix": "jsfo",
    "body": "fontWeight: '${1:normal}',",
    "description": "fontWeight"
  },
  "height": {
    "prefix": "jsh",
    "body": "height: ${1},",
    "description": "height"
  },
  "left": {
    "prefix": "jsl",
    "body": "left: ${1},",
    "description": "left"
  },
  "margin": {
    "prefix": "jsmar",
    "body": "margin: '${1}',",
    "description": "margin"
  },
  "marginBottom": {
    "prefix": "jsmar",
    "body": "marginBottom: ${1},",
    "description": "marginBottom"
  },
  "marginHorizontal": {
    "prefix": "jsmar",
    "body": "marginHorizontal: '${1}',",
    "description": "marginHorizontal"
  },
  "marginLeft": {
    "prefix": "jsmar",
    "body": "marginLeft: ${1},",
    "description": "marginLeft"
  },
  "marginRight": {
    "prefix": "jsmar",
    "body": "marginRight: ${1},",
    "description": "marginRight"
  },
  "marginTop": {
    "prefix": "jsmar",
    "body": "marginTop: ${1},",
    "description": "marginTop"
  },
  "marginVertical": {
    "prefix": "jsmar",
    "body": "marginVertical: '${1}',",
    "description": "marginVertical"
  },
  "maxHeight": {
    "prefix": "jsmax",
    "body": "maxHeight: ${1},",
    "description": "maxHeight"
  },
  "maxWidth": {
    "prefix": "jsmax",
    "body": "maxWidth: ${1},",
    "description": "maxWidth"
  },
  "minHeight": {
    "prefix": "jsmin",
    "body": "minHeight: ${1},",
    "description": "minHeight"
  },
  "minWidth": {
    "prefix": "jsmin",
    "body": "minWidth: ${1},",
    "description": "minWidth"
  },
  "overflow": {
    "prefix": "jsover",
    "body": "overflow: '${1}',",
    "description": "overflow"
  },
  "padding": {
    "prefix": "jspadding",
    "body": "padding: ${1},",
    "description": "padding"
  },
  "paddingBottom": {
    "prefix": "jspadding",
    "body": "paddingBottom: ${1},",
    "description": "paddingBottom"
  },
  "paddingHorizontal": {
    "prefix": "jspadding",
    "body": "paddingHorizontal: ${1},",
    "description": "paddingHorizontal"
  },
  "paddingLeft": {
    "prefix": "jspadding",
    "body": "paddingLeft: ${1},",
    "description": "paddingLeft"
  },
  "paddingRight": {
    "prefix": "jspadding",
    "body": "paddingRight: ${1},",
    "description": "paddingRight"
  },
  "paddingTop": {
    "prefix": "jspadding",
    "body": "paddingTop: ${1},",
    "description": "paddingTop"
  },
  "paddingVertical": {
    "prefix": "jspadding",
    "body": "paddingVertical: ${1},",
    "description": "paddingVertical"
  },
  "position": {
    "prefix": "jspos",
    "body": "position: ${1},",
    "description": "position"
  },
  "right": {
    "prefix": "jsri",
    "body": "right: ${1},",
    "description": "right"
  },
  "top": {
    "prefix": "jstop",
    "body": "top: ${1},",
    "description": "top"
  },
  "width": {
    "prefix": "jsw",
    "body": "width: ${1},",
    "description": "width"
  },
  "zIndex": {
    "prefix": "jsz",
    "body": "zIndex: ${1},",
    "description": "zIndex"
  },
  "direction": {
    "prefix": "jsdi",
    "body": "direction: ${1},",
    "description": "direction"
  },
  "barStyle": {
    "prefix": "jsbar",
    "body": "barStyle = '${1:light-content}'",
    "description": "barStyle"
  },
  "import redux statement": {
    "prefix": "jsrx",
    "body": [
      "import { connect } from 'react-redux';",
      ""
    ],
    "description": "import { connect } from 'react-redux';"
  },
  "mappingToProps": {
    "prefix": "jsrxmap",
    "body": [
      "const mapStateToProps = (state) => ({",
      "",
      "});",
      "const mapDispatchToProps = (dispatch) => ({",
      "",
      "});"
    ]
  },
  "reduxAction": {
    "prefix": "jsrxaction",
    "body": [
      "export const ${1:actionName} = (${2:param}) => ({",
      "  type: ${3:type},",
      "  payload: ${4:payload}",
      "})",
      ""
    ]
  },
  "reduxConst": {
    "prefix": "jsrxconst",
    "body": "export const ${1:constantName} = '${1:constantName}';"
  },
  "reduxReducer": {
    "prefix": "jsrxreducer",
    "body": [
      "const initialState = {",
      "",
      "}",
      "",
      "export default (state = initialState, action) => {",
      "  switch (action.type) {",
      "",
      "  case ${1:typeName}:",
      "    return { ...state };",
      "",
      "  default:",
      "    return state",
      "  }",
      "};",
      ""
    ]
  },
  "reduxSelector": {
    "prefix": "jsrxselect",
    "body": [
      "import { createSelector } from 'reselect';",
      "",
      "export const ${1:selectorName} = state => state.${2:selector}",
      ""
    ]
  },
  "reactComponent": {
    "prefix": "jsrcc",
    "body": [
      "import React, { Component } from 'react';",
      "",
      "export default class ${1:componentName} extends Component {",
      "  render() {",
      "    return (",
      "      <div> ${2:textInComponent} </div>",
      "    );",
      "  }",
      "}",
      ""
    ],
    "description": "React Component"
  },
  "reactComponentExport": {
    "prefix": "jsrce",
    "body": [
      "import React, { Component } from 'react';",
      "",
      "class ${1:componentName} extends Component {",
      "  render() {",
      "    return (",
      "      <div> ${2:textInComponent} </div>",
      "    );",
      "  }",
      "}",
      "",
      "export default ${1:componentName};",
      ""
    ],
    "description": "React Component Export"
  },
  "import React": {
    "prefix": "jsimr",
    "body": [
      "import React from 'react';",
      ""
    ],
    "description": "import React from 'react';"
  },
  "import React, { Component }": {
    "prefix": "jsimrc",
    "body": [
      "import React, { Component } from 'react';",
      ""
    ],
    "description": "import React, { Component } from 'react';"
  },
  "Import React-Native Element": {
    "prefix": "jsimrn",
    "body": "import { $1 } from 'react-native';",
    "description": "Import React-Native Element"
  },
  "import React, { Component } & PropTypes": {
    "prefix": "jsimrcp",
    "body": [
      "import React, { Component } from 'react';",
      "import PropTypes from 'prop-types';",
      ""
    ]
  },
  "import React, { PureComponent }": {
    "prefix": "jsimrpc",
    "body": [
      "import React, { PureComponent } from 'react';",
      ""
    ],
    "description": "import React, { PureComponent } from 'react';"
  },
  "import React, { PureComponent } & PropTypes": {
    "prefix": "jsimrpcp",
    "body": [
      "import React, { PureComponent } from 'react';",
      "import PropTypes from 'prop-types';",
      ""
    ],
    "description": [
      "import React, { PureComponent } from 'react';",
      "import PropTypes from 'prop-types';",
      ""
    ]
  },
  "classConstructor": {
    "prefix": "jsrconst",
    "body": [
      "constructor(props) {",
      "  super(props)",
      "",
      "  this.state = {",
      "     $0",
      "  };",
      "};",
      ""
    ],
    "description": "Adds a default constructor for it('', () => {})the class that contains props as arguments"
  },
  "emptyState": {
    "prefix": "jsest",
    "body": [
      "this.state = {",
      "  $1",
      "};",
      ""
    ],
    "description": "Creates empty state object. To be used in a constructor."
  },
  "componentWillMount": {
    "prefix": "jscwm",
    "body": [
      "componentWillMount = () => {",
      "  $0",
      "};",
      ""
    ],
    "description": "Invoked once, both on the client and server, immediately before the initial rendering occurs"
  },
  "componentDidMount": {
    "prefix": "jscdm",
    "body": [
      "componentDidMount = () => {",
      "  $0",
      "};",
      ""
    ],
    "description": "Invoked once, only on the client (not on the server), immediately after the initial rendering occurs."
  },
  "componentWillReceiveProps": {
    "prefix": "jscwr",
    "body": [
      "componentWillReceiveProps = (nextProps) => {",
      "  $0",
      "};",
      ""
    ],
    "description": "Invoked when a component is receiving new props. This method is not called for the initial render."
  },
  "shouldComponentUpdate": {
    "prefix": "jsscu",
    "body": [
      "shouldComponentUpdate = (nextProps, nextState) => {",
      "  $0",
      "};",
      ""
    ],
    "description": "Invoked before rendering when new props or state are being received. "
  },
  "componentWillUpdate": {
    "prefix": "jscwup",
    "body": [
      "componentWillUpdate = (nextProps, nextState) => {",
      "  $0",
      "};",
      ""
    ],
    "description": "Invoked immediately before rendering when new props or state are being received."
  },
  "componentDidUpdate": {
    "prefix": "jscdup",
    "body": [
      "componentDidUpdate = (prevProps, prevState) => {",
      "  $0",
      "};",
      ""
    ],
    "description": "Invoked immediately after the component's updates are flushed to the DOM."
  },
  "componentWillUnmount": {
    "prefix": "jscwun",
    "body": [
      "componentWillUnmount = () => {",
      "  $0",
      "};",
      ""
    ],
    "description": "Invoked immediately before a component is unmounted from the DOM."
  },
  "componentRender": {
    "prefix": "jsren",
    "body": [
      "render() {",
      "  return (",
      "    <div>",
      "      $0",
      "    </div>",
      "  )",
      "};"
    ],
    "description": "Basic render."
  },
  "componentSetStateObject": {
    "prefix": "jssst",
    "body": "this.setState({$0})",
    "description": "Performs a shallow merge of nextState into current state"
  },
  "componentSetStateFunc": {
    "prefix": "jsssf",
    "body": [
      "this.setState((state, props) => { return { $0 }})",
      ""
    ],
    "description": "Performs a shallow merge of nextState into current state"
  },
  "import": {
    "prefix": "jsimp",
    "body": "import ${2:moduleName} from '${1:module}';$0"
  },
  "importNoModuleName": {
    "prefix": "jsimn",
    "body": "import '${1:module}';$0"
  },
  "importDestructing": {
    "prefix": "jsimd",
    "body": "import { $2 } from '${1:module}';$0"
  },
  "importEverything": {
    "prefix": "jsime",
    "body": "import * as ${2:alias} from '${1:module}';$0"
  },
  "importAs": {
    "prefix": "jsima",
    "body": "import { ${2:originalName} as ${3:alias} } from '${1:module}';$0"
  },
  "exportDefault": {
    "prefix": "jsexp",
    "body": "export default $1$0"
  },
  "exportDestructing": {
    "prefix": "jsexd",
    "body": "export { $2 } from '${1:module}';$0"
  },
  "exportAs": {
    "prefix": "jsexa",
    "body": "export { ${2:originalName} as ${3:alias} } from '${1:module}';$0"
  },
  "exportNamedFunction": {
    "prefix": "jsenf",
    "body": [
      "export const ${1:functionName} = (${2:params}) => {",
      "  $0",
      "};",
      ";"
    ],
    "description": "Export named function in ES7 syntax"
  },
  "exportDefaultFunction": {
    "prefix": "jsedf",
    "body": [
      "export default (${1:params}) => {",
      "  $0",
      "};",
      ""
    ],
    "description": "Export default function in ES7 syntax"
  },
  "method": {
    "prefix": "jsmet",
    "body": [
      "${1:methodName} = (${2:params}) => {",
      "  ${0};",
      "};",
      ""
    ],
    "description": "Creates a method inside a class in ES7 syntax"
  },
  "propertyGet": {
    "prefix": "jspge",
    "body": [
      "get ${1:propertyName} = () => {",
      "  return this.${0};",
      "};",
      ""
    ],
    "description": "Creates a getter property inside a class in ES7 syntax"
  },
  "propertyset": {
    "prefix": "jspse",
    "body": [
      "set ${1:propertyName} = (${2:value}) => {",
      "  ${0};",
      "}",
      ""
    ],
    "description": "Creates a setter property inside a class in ES7 syntax"
  },
  "forEach": {
    "prefix": "jsfre",
    "body": [
      "${1:array}.forEach(${2:currentItem} => {",
      "  ${0}",
      "})",
      ""
    ],
    "description": "Creates a forEach statement in ES7 syntax"
  },
  "forOf": {
    "prefix": "jsfof",
    "body": [
      "for(let ${1:item} of ${2:object}) {",
      "  ${0}",
      "}",
      ""
    ],
    "description": "Iterating over property names of iterable objects"
  },
  "forIn": {
    "prefix": "jsfin",
    "body": [
      "for(let ${1:item} in ${2:object}) {",
      "  ${0}",
      "}",
      ""
    ],
    "description": "Iterating over property values of iterable objects"
  },
  "anonymousFunction": {
    "prefix": "jsanfn",
    "body": [
      "(${1:params}) => {",
      "  ${2}",
      "}",
      ""
    ],
    "description": "Creates an anonymous function in ES7 syntax"
  },
  "namedFunction": {
    "prefix": "jsnfn",
    "body": [
      "const ${1:name} = (${2:params}) => {",
      "  ${3}",
      "}",
      ""
    ],
    "description": "Creates a named function in ES7 syntax"
  },
  "destructingObject": {
    "prefix": "jsdob",
    "body": "const {${1:propertyName}} = ${2:objectToDestruct}",
    "description": "Creates and assigns a local variable using object destructing"
  },
  "destructingArray": {
    "prefix": "jsdar",
    "body": "const [${1:propertyName}] = ${2:arrayToDestruct};",
    "description": "Creates and assigns a local variable using array destructing"
  },
  "setInterval": {
    "prefix": "jssti",
    "body": [
      "setInterval(() => {",
      "  ${2}",
      "}, ${0:intervalInms})",
      ""
    ],
    "description": "Executes the given function at specified intervals in ES7 syntax"
  },
  "setTimeOut": {
    "prefix": "jssto",
    "body": [
      "setTimeout(() => {",
      "  ${2}",
      "}, ${1:delayInms})",
      ""
    ],
    "description": "Executes the given function after the specified delay in ES7 syntax"
  },
  "promise": {
    "prefix": "jsprom",
    "body": [
      "return new Promise((resolve, reject) => {",
      "  ${1}",
      "})",
      ""
    ],
    "description": "Creates and returns a new Promise in the standard ES7 syntax"
  },
  "consoleAssert": {
    "prefix": "jscas",
    "body": "console.assert(${1:expression}, ${2:object})",
    "description": "If the specified expression is false, the message is written to the console along with a stack trace"
  },
  "consoleClear": {
    "prefix": "jsccl",
    "body": "console.clear()",
    "description": "Clears the console"
  },
  "consoleCount": {
    "prefix": "jscco",
    "body": "console.count(${1:label})",
    "description": "Writes the the number of times that count() has been invoked at the same line and with the same label"
  },
  "consoleDir": {
    "prefix": "jscdi",
    "body": "console.dir(${1:object})",
    "description": "Prints a JavaScript representation of the specified object"
  },
  "consoleError": {
    "prefix": "jscer",
    "body": "console.error(${1:object})",
    "description": "Displays a message in the console and also includes a stack trace from where the method was called"
  },
  "consoleGroup": {
    "prefix": "jscgr",
    "body": "console.group(\"${1:label}\")",
    "description": "Groups and indents all following output by an additional level, until console.groupEnd() is called."
  },
  "consoleGroupEnd": {
    "prefix": "jscge",
    "body": "console.groupEnd()",
    "description": "Closes out the corresponding console.group()."
  },
  "consoleLog": {
    "prefix": "jsclg",
    "body": "console.log(${1:object})",
    "description": "Displays a message in the console"
  },
  "consoleTrace": {
    "prefix": "jsctr",
    "body": "console.trace(${1:object})",
    "description": "Prints a stack trace from the point where the method was called"
  },
  "consoleWarn": {
    "prefix": "jscwa",
    "body": "console.warn(${1:object})",
    "description": "Displays a message in the console but also displays a yellow warning icon along with the logged message"
  },
  "consoleInfo": {
    "prefix": "jscin",
    "body": "console.info(${1:object})",
    "description": "Displays a message in the console but also displays a blue information icon along with the logged message"
  },
  "ImportPropTypes": {
    "prefix": "jsipt",
    "body": "import PropTypes from 'prop-types';",
    "description": "import PropTypes from 'prop-types';"
  },
  "PropTypes": {
    "prefix": "jspt",
    "body": [
      "${1}.propTypes = {",
      "",
      "};"
    ],
    "description": "Create PropTypes"
  },
  "defaultProps": {
    "prefix": "jsdfp",
    "body": [
      "${1}.defaultProps = {",
      "",
      "};"
    ],
    "description": "Create Default Props"
  },
  "propTypeArray": {
    "prefix": "jspta",
    "body": "PropTypes.array,",
    "description": "Array prop type"
  },
  "propTypeArrayRequired": {
    "prefix": "jsptar",
    "body": "PropTypes.array.isRequired,",
    "description": "Array prop type required"
  },
  "propTypeBool": {
    "prefix": "jsptb",
    "body": "PropTypes.bool,",
    "description": "Bool prop type"
  },
  "propTypeBoolRequired": {
    "prefix": "jsptbr",
    "body": "PropTypes.bool.isRequired,",
    "description": "Bool prop type required"
  },
  "propTypeFunc": {
    "prefix": "jsptf",
    "body": "PropTypes.func,",
    "description": "Func prop type"
  },
  "propTypeFuncRequired": {
    "prefix": "jsptfr",
    "body": "PropTypes.func.isRequired,",
    "description": "Func prop type required"
  },
  "propTypeNumber": {
    "prefix": "jsptn",
    "body": "PropTypes.number,",
    "description": "Number prop type"
  },
  "propTypeNumberRequired": {
    "prefix": "jsptnr",
    "body": "PropTypes.number.isRequired,",
    "description": "Number prop type required"
  },
  "propTypeObject": {
    "prefix": "jspto",
    "body": "PropTypes.object,",
    "description": "Object prop type"
  },
  "propTypeObjectRequired": {
    "prefix": "jsptor",
    "body": "PropTypes.object.isRequired,",
    "description": "Object prop type required"
  },
  "propTypeString": {
    "prefix": "jspts",
    "body": "PropTypes.string,",
    "description": "String prop type"
  },
  "propTypeStringRequired": {
    "prefix": "jsptsr",
    "body": "PropTypes.string.isRequired,",
    "description": "String prop type required"
  },
  "propTypeNode": {
    "prefix": "jsptnd",
    "body": "PropTypes.node,",
    "description": "Anything that can be rendered: numbers, strings, elements or an array"
  },
  "propTypeNodeRequired": {
    "prefix": "jsptndr",
    "body": "PropTypes.node.isRequired,",
    "description": "Anything that can be rendered: numbers, strings, elements or an array required"
  },
  "propTypeElement": {
    "prefix": "jsptel",
    "body": "PropTypes.element,",
    "description": "React element prop type"
  },
  "propTypeElementRequired": {
    "prefix": "jsptelr",
    "body": "PropTypes.element.isRequired,",
    "description": "React element prop type required"
  },
  "propTypeInstanceOf": {
    "prefix": "jspti",
    "body": "PropTypes.instanceOf($0),",
    "description": "Is an instance of a class prop type"
  },
  "propTypeInstanceOfRequired": {
    "prefix": "jsptir",
    "body": "PropTypes.instanceOf($0).isRequired,",
    "description": "Is an instance of a class prop type required"
  },
  "propTypeEnum": {
    "prefix": "jspte",
    "body": "PropTypes.oneOf(['$0']),",
    "description": "Prop type limited to specific values by treating it as an enum"
  },
  "propTypeEnumRequired": {
    "prefix": "jspter",
    "body": "PropTypes.oneOf(['$0']).isRequired,",
    "description": "Prop type limited to specific values by treating it as an enum required"
  },
  "propTypeOneOfType": {
    "prefix": "jsptet",
    "body": [
      "PropTypes.oneOfType([",
      "  $0",
      "]),"
    ],
    "description": "An object that could be one of many types"
  },
  "propTypeOneOfTypeRequired": {
    "prefix": "jsptetr",
    "body": [
      "PropTypes.oneOfType([",
      "  $0",
      "]).isRequired,"
    ],
    "description": "An object that could be one of many types required"
  },
  "propTypeArrayOf": {
    "prefix": "jsptao",
    "body": "PropTypes.arrayOf($0),",
    "description": "An array of a certain type"
  },
  "propTypeArrayOfRequired": {
    "prefix": "jsptaor",
    "body": "PropTypes.arrayOf($0).isRequired,",
    "description": "AcomponentNamen array of a certain type required"
  },
  "propTypeObjectOf": {
    "prefix": "jsptoo",
    "body": "PropTypes.objectOf($0),",
    "description": "An object with property values of a certain type"
  },
  "propTypeObjectOfRequired": {
    "prefix": "jsptoor",
    "body": "PropTypes.objectOf($0).isRequired,",
    "description": "An object with property values of a certain type required"
  },
  "propTypeShape": {
    "prefix": "jsptsh",
    "body": [
      "PropTypes.shape({",
      "  $0",
      "}),"
    ],
    "description": "An object taking on a particular shape"
  },
  "propTypeShapeRequired": {
    "prefix": "jsptshr",
    "body": [
      "PropTypes.shape({",
      "  $0",
      "}).isRequired,"
    ],
    "description": "An object taking on a particular shape required"
  },
  "Comment Big Block": {
    "prefix": "jscmmb",
    "body": [
      "/**",
      "|--------------------------------------------------",
      "| $1",
      "|--------------------------------------------------",
      "*/"
    ]
  },
  "Full Region Block": {
    "prefix": "jsfregion",
    "body": [
      "// #region ${1:title}",
      "",
      "${2}",
      "",
      "// #endregion $0"
    ]
  },
  "describeBlock": {
    "prefix": "jsdesc",
    "body": [
      "describe('$1', () => {",
      "  $0",
      "})",
      ""
    ],
    "description": "Testing `describe` block"
  },
  "testBlock": {
    "prefix": "jstest",
    "body": [
      "test('should $1', () => {",
      "  $0",
      "})",
      ""
    ],
    "description": "Testing `test` block"
  },
  "itBlock": {
    "prefix": "jstit",
    "body": [
      "it('should $1', () => {",
      "  $0",
      "})",
      ""
    ],
    "description": "Testing `it` block"
  },
  "setupTest": {
    "prefix": "jsstest",
    "body": [
      "import { ${1:ComponentName}, mapStateToProps, mapDispatchToProps } from '../${1:ComponentName}';",
      "",
      "describe('<${1:ComponentName} />', () => {",
      "  const defaultProps = {",
      "",
      "  };",
      "",
      "  const setup = buildSetup(${1:ComponentName}, defaultProps)",
      "",
      "  test('render', () => {",
      "    expect(setup().wrapper).toMatchSnapshot()",
      "  })",
      "})",
      ""
    ]
  },
  "setupTestWithEnzymeToJson": {
    "prefix": "jssjtest",
    "body": [
      "import toJson from 'enzyme-to-json';",
      "import { ${1:ComponentName}, mapStateToProps, mapDispatchToProps } from '../${1:ComponentName}';",
      "",
      "describe('<${1:ComponentName} />', () => {",
      "  const defaultProps = {",
      "",
      "  };",
      "",
      "  const setup = buildSetup(${1:ComponentName}, defaultProps)",
      "",
      "  test('render', () => {",
      "    expect(toJson(setup().wrapper)).toMatchSnapshot()",
      "  })",
      "})",
      ""
    ]
  },
  "setupReactNativeTest": {
    "prefix": "jssntest",
    "body": [
      "import 'react-native';",
      "import React from 'react';",
      "import renderer from 'react-test-renderer';",
      "",
      "import ${1:ComponentName} from '../${1:ComponentName}';",
      "",
      "it('renders correctly', () =>{",
      "const tree = renderer.create(<${1:ComponentName} />).toJSON()",
      "",
      "expect(tree).toMatchSnapshot()",
      "})",
      ""
    ]
  },
  "graphQLForComponent": {
    "prefix": "jsgraphql",
    "body": [
      "import { compose, graphql } from 'react-apollo';",
      ""
    ]
  },
  "exportGraphQL": {
    "prefix": "jsexpgql",
    "body": [
      "export default compose(",
      "  graphql(${1:queryOrMutation}, { name: ${2:name} }),",
      ")(${3:ComponentName})"
    ]
  },
  "hocComponentWithRedux": {
    "prefix": "jshocredux",
    "body": [
      "import React from 'react';",
      "import PropTypes from 'prop-types';",
      "import { connect } from 'react-redux';",
      "",
      "export const mapStateToProps = state => ({",
      "",
      "})",
      "",
      "export const mapDispatchToProps = {",
      " ",
      "};",
      "",
      "export const ${1:hocComponentName} = (WrappedComponent) => {",
      "  const hocComponent = ({ ...props }) => <WrappedComponent {...props} />",
      "",
      "  hocComponent.propTypes = {",
      "  };",
      "",
      "  return hocComponent",
      "};",
      "",
      "export default WrapperComponent => connect(mapStateToProps, mapDispatchToProps)(${1:hocComponentName}(WrapperComponent))",
      ""
    ]
  },
  "hocComponent": {
    "prefix": "jshoc",
    "body": [
      "import React from 'react';",
      "import PropTypes from 'prop-types';",
      "",
      "export default (WrappedComponent) => {",
      "  const hocComponent = ({ ...props }) => <WrappedComponent {...props} />",
      "",
      "  hocComponent.propTypes = {",
      "  };",
      "",
      "  return hocComponent",
      "};",
      ""
    ]
  },
  "EslintDisableLine": {
    "prefix": "jsedl",
    "body": "// eslint-disable-line",
    "description": "Eslint Disable Line"
  },
  "Comment Block": {
    "prefix": "jscm",
    "body": [
      "/**",
      " * ${1}",
      " */"
    ]
  },
  "LoremIpsumOnce": {
    "prefix": "jsli1",
    "body": "Lorem Ipsum is simply dummy text of the printing and typesetting industry.",
    "description": "Lorem Ipsum is simply dummy text of the printing and typesetting industry."
  },
  "LoremIpsumTwo": {
    "prefix": "jsli2",
    "body": [
      "Lorem Ipsum is simply dummy text of the printing and typesetting industry.",
      "Lorem Ipsum has been the industry's standard dummy text ever since the 1500s, when an unknown printer took a galley of type and scrambled it to make a type specimen book."
    ],
    "description": [
      "Lorem Ipsum is simply dummy text of the printing and typesetting industry.",
      "Lorem Ipsum has been the industry's standard dummy text ever since the 1500s, when an unknown printer took a galley of type and scrambled it to make a type specimen book."
    ]
  },
  "LoremIpsumThree": {
    "prefix": "jsli3",
    "body": [
      "Lorem Ipsum is simply dummy text of the printing and typesetting industry.",
      "Lorem Ipsum has been the industry standard dummy text ever since the 1500s, when an unknown printer took a galley of type and scrambled it to make a type specimen book.",
      "It has survived not only five centuries, but also the leap into electronic typesetting, remaining essentially unchanged."
    ],
    "description": [
      "Lorem Ipsum is simply dummy text of the printing and typesetting industry.",
      "Lorem Ipsum has been the industry standard dummy text ever since the 1500s, when an unknown printer took a galley of type and scrambled it to make a type specimen book.",
      "It has survived not only five centuries, but also the leap into electronic typesetting, remaining essentially unchanged."
    ]
  },
  "LoremIpsumFour": {
    "prefix": "jsli4",
    "body": [
      "Lorem Ipsum is simply dummy text of the printing and typesetting industry.",
      "Lorem Ipsum has been the industry standard dummy text ever since the 1500s, when an unknown printer took a galley of type and scrambled it to make a type specimen book.",
      "It has survived not only five centuries, but also the leap into electronic typesetting, remaining essentially unchanged.",
      "It was popularised in the 1960s with the release of Letraset sheets containing Lorem Ipsum passages, and more recently with desktop publishing software like Aldus PageMaker including versions of Lorem Ipsum."
    ],
    "description": [
      "Lorem Ipsum is simply dummy text of the printing and typesetting industry.",
      "Lorem Ipsum has been the industry standard dummy text ever since the 1500s, when an unknown printer took a galley of type and scrambled it to make a type specimen book.",
      "It has survived not only five centuries, but also the leap into electronic typesetting, remaining essentially unchanged.",
      "It was popularised in the 1960s with the release of Letraset sheets containing Lorem Ipsum passages, and more recently with desktop publishing software like Aldus PageMaker including versions of Lorem Ipsum."
    ]
  },
  "LoremIpsumFive": {
    "prefix": "jsli5",
    "body": [
      "Lorem Ipsum is simply dummy text of the printing and typesetting industry.",
      "Lorem Ipsum has been the industry's standard dummy text ever since the 1500s, when an unknown printer took a galley of type and scrambled it to make a type specimen book.",
      "It has survived not only five centuries, but also the leap into electronic typesetting, remaining essentially unchanged.",
      "It was popularised in the 1960s with the release of Letraset sheets containing Lorem Ipsum passages, and more recently with desktop publishing software like Aldus PageMaker including versions of Lorem Ipsum.",
      "The standard chunk of Lorem Ipsum used since the 1500s is reproduced below for those interested. Sections 1.10.32 and 1.10.33 from de Finibus Bonorum et Malorum by Cicero are also reproduced in their exact original form, accompanied by English versions from the 1914 translation by H. Rackham."
    ],
    "description": [
      "Lorem Ipsum is simply dummy text of the printing and typesetting industry.",
      "Lorem Ipsum has been the industry's standard dummy text ever since the 1500s, when an unknown printer took a galley of type and scrambled it to make a type specimen book.",
      "It has survived not only five centuries, but also the leap into electronic typesetting, remaining essentially unchanged.",
      "It was popularised in the 1960s with the release of Letraset sheets containing Lorem Ipsum passages, and more recently with desktop publishing software like Aldus PageMaker including versions of Lorem Ipsum.",
      "The standard chunk of Lorem Ipsum used since the 1500s is reproduced below for those interested. Sections 1.10.32 and 1.10.33 from de Finibus Bonorum et Malorum by Cicero are also reproduced in their exact original form, accompanied by English versions from the 1914 translation by H. Rackham."
    ]
  }
}
